intake_hive/__init__.py
intake_hive/hive_source.py
intake_hive/tests/catalog.yaml
intake_hive/tests/conftest.py
intake_hive/tests/dal-catalog.yaml
intake_hive/tests/data/user_events.csv
intake_hive/tests/test_hive_source.py
intake_hive-0.1.1.dist-info/entry_points.txt
intake_hive-0.1.1.dist-info/LICENSE
intake_hive-0.1.1.dist-info/WHEEL
intake_hive-0.1.1.dist-info/METADATA
intake_hive-0.1.1.dist-info/RECORD
