Metadata-Version: 2.1
Name: intake-hive
Version: 0.1.1
Summary: Intake Hive DataSource Plugin.
Author: Zillow AI Platform
Requires-Python: >=3.6
Classifier: Development Status :: 2 - Pre-Alpha
Classifier: Intended Audience :: Developers
Classifier: License :: OSI Approved :: Apache Software License
Classifier: Natural Language :: English
Classifier: Programming Language :: Python :: 3
Classifier: Programming Language :: Python :: 3.6
Classifier: Programming Language :: Python :: 3.7
Classifier: Programming Language :: Python :: 3.8
Provides-Extra: doc
Requires-Dist: intake (>=0.5.3)
Requires-Dist: pyspark (>=2.3.0)
